spam_doggy/__init__.py
spam_doggy/spam_doggy.py
spam_doggy/datasets/__init__.py
spam_doggy/datasets/data_loader.py
spam_doggy-1.0.1.dist-info/LICENSE
spam_doggy-1.0.1.dist-info/METADATA
spam_doggy-1.0.1.dist-info/WHEEL
spam_doggy-1.0.1.dist-info/top_level.txt
spam_doggy-1.0.1.dist-info/RECORD
