Metadata-Version: 2.1
Name: spam-doggy
Version: 1.0.1
Summary: Spam Doggy is a spam classifier that uses a Naive Bayes classifier to classify emails as spam or not spam.
Home-page: https://github.com/teixeirazeus/Spam-Doggy
Author: teixeirazeus
License: MIT
Project-URL: Issue tracker, https://github.com/teixeirazeus/Spam-Doggy/issues
Classifier: Development Status :: 5 - Production/Stable
Classifier: Topic :: Scientific/Engineering :: Artificial Intelligence
Classifier: License :: OSI Approved :: MIT License
Classifier: Intended Audience :: Developers
Classifier: Natural Language :: English
Classifier: Operating System :: OS Independent
Classifier: Programming Language :: Python :: 3
Classifier: Programming Language :: Python :: 3.8
Classifier: Programming Language :: Python :: 3.9
Classifier: Programming Language :: Python :: 3.10
Classifier: Programming Language :: Python :: 3.11
Classifier: Topic :: Software Development :: Libraries
Classifier: Topic :: Software Development :: Libraries :: Python Modules
Classifier: Topic :: Utilities
Requires-Python: >=3.7
License-File: LICENSE
Requires-Dist: pandas
Requires-Dist: scikit-learn
Requires-Dist: joblib
